ab/__init__.py
ab/__main__.py
ab/flash.py
ab/miniterm.py
ab/pyboard.py
ampy_batch_tool-0.7.16.dist-info/LICENSE
ampy_batch_tool-0.7.16.dist-info/METADATA
ampy_batch_tool-0.7.16.dist-info/WHEEL
ampy_batch_tool-0.7.16.dist-info/entry_points.txt
ampy_batch_tool-0.7.16.dist-info/top_level.txt
ampy_batch_tool-0.7.16.dist-info/RECORD
