Metadata-Version: 2.1
Name: ampy-batch-tool
Version: 0.7.16
Summary: An adafruit-ampy batch tool
Home-page: https://gitee.com/walkline/a-batch-tool
Author: Walkline Wang
Author-email: walkline@163.com
Classifier: Programming Language :: Python :: 3
Classifier: License :: OSI Approved :: MIT License
Classifier: Operating System :: Microsoft :: Windows
Classifier: Environment :: Console
Provides: ab
License-File: LICENSE
Requires-Dist: pyserial
Requires-Dist: pywin32
Requires-Dist: esptool >=3.1
